pycatflow/__init__.py
pycatflow/input.py
pycatflow/viz.py
pycatflow-0.2.1.dist-info/licenses/LICENSE
tests/__init__.py
tests/test_integration.py
tests/test_visualization.py
pycatflow-0.2.1.dist-info/METADATA
pycatflow-0.2.1.dist-info/WHEEL
pycatflow-0.2.1.dist-info/top_level.txt
pycatflow-0.2.1.dist-info/RECORD
